[
  {
    "timestamp": "2020-06-30 17:17:28",
    "log_lvl": "INFO",
    "log_msg": "Initial log",
    "log_detail": ""
  },
  {
    "timestamp": "2020-06-30 17:17:28",
    "log_lvl": "INFO",
    "log_msg": "session started",
    "log_detail": "session has started",
    "event": "session start",
    "sessionid": "98d271fb1962aab027ff839d01e8692a"
  },
  {
    "timestamp": "2020-06-30 17:17:34",
    "log_lvl": "INFO",
    "log_msg": "uploadresults",
    "log_detail": "Number of plots (rows):12, Number of species (columns):148, Number of plots (rows) with environmental data detected:12\n                   , Number of plots (rows) with spatial data detected:12",
    "event": "upload",
    "sessionid": "98d271fb1962aab027ff839d01e8692a",
    "Numplots": 12,
    "Numspecies": 148,
    "NumplotsWithEnvData": 12,
    "NumplotsWithSpatialData": 12,
    "custom_log_lvl": false
  },
  {
    "timestamp": "2020-06-30 17:17:35",
    "log_lvl": "INFO",
    "log_msg": "uploadresults",
    "log_detail": "Species names not found in eastern NSW PCT standardised taxonomy:There are 148 species, <b><mark> and 1 could not be found: Pratpurp, so were ignored in analysis.<\/mark><\/b>, Sites outside eastern NSW study region:0",
    "event": "upload",
    "sessionid": "98d271fb1962aab027ff839d01e8692a",
    "MissingSpeciesList": "There are 148 species, <b><mark> and 1 could not be found: Pratpurp, so were ignored in analysis.<\/mark><\/b>",
    "NumplotsOutsideStudy": "0"
  },
  {
    "timestamp": "2020-06-30 17:38:00",
    "log_lvl": "INFO",
    "log_msg": "session started",
    "log_detail": "session has started",
    "event": "session start",
    "sessionid": "1a0a9869f6dd0a40dde1bf0069bb912c"
  },
  {
    "timestamp": "2020-06-30 17:38:02",
    "log_lvl": "INFO",
    "log_msg": "session has ended",
    "log_detail": "session has ended",
    "sessionid": "98d271fb1962aab027ff839d01e8692a"
  },
  {
    "timestamp": "2020-06-30 17:38:10",
    "log_lvl": "INFO",
    "log_msg": "uploadresults",
    "log_detail": "Number of plots (rows):12, Number of species (columns):148, Number of plots (rows) with environmental data detected:12\n                   , Number of plots (rows) with spatial data detected:12",
    "event": "upload",
    "sessionid": "1a0a9869f6dd0a40dde1bf0069bb912c",
    "Numplots": 12,
    "Numspecies": 148,
    "NumplotsWithEnvData": 12,
    "NumplotsWithSpatialData": 12,
    "custom_log_lvl": false
  },
  {
    "timestamp": "2020-06-30 17:38:11",
    "log_lvl": "INFO",
    "log_msg": "uploadresults",
    "log_detail": "Species names not found in eastern NSW PCT standardised taxonomy:There are 148 species, <b><mark> and 1 could not be found: Pratpurp, so were ignored in analysis.<\/mark><\/b>, Sites outside eastern NSW study region:0",
    "event": "upload",
    "sessionid": "1a0a9869f6dd0a40dde1bf0069bb912c",
    "MissingSpeciesList": "There are 148 species, <b><mark> and 1 could not be found: Pratpurp, so were ignored in analysis.<\/mark><\/b>",
    "NumplotsOutsideStudy": "0"
  },
  {
    "timestamp": "2020-06-30 17:39:50",
    "log_lvl": "INFO",
    "log_msg": "session has ended",
    "log_detail": "session has ended",
    "sessionid": "1a0a9869f6dd0a40dde1bf0069bb912c"
  }
]
